<?xml version="1.0" encoding="UTF-8"?><record_update>
    <sys_ui_section action="DELETE" caption="Notes" section_id="8f0f4e89db17ff006c66d211ce9619c1" sys_domain="global" table="x_soud2_manual_bil_manual_billing_header" version="3" view="">
        <sys_ui_element action="INSERT_OR_UPDATE">
            <element>description</element>
            <position>0</position>
            <sys_created_by>dyearsley</sys_created_by>
            <sys_created_on>2019-10-03 20:42:06</sys_created_on>
            <sys_id>a10f9c19dbdc44107adf5dd5ce96195d</sys_id>
            <sys_mod_count>0</sys_mod_count>
            <sys_ui_formatter/>
            <sys_ui_section caption="Notes" display_value="Notes" name="x_soud2_manual_bil_manual_billing_header" sys_domain="global" view="Default view">8f0f4e89db17ff006c66d211ce9619c1</sys_ui_section>
            <sys_updated_by>dyearsley</sys_updated_by>
            <sys_updated_on>2019-10-03 20:42:06</sys_updated_on>
            <sys_user/>
            <type/>
        </sys_ui_element>
        <sys_ui_section action="DELETE">
            <caption>Notes</caption>
            <header>false</header>
            <name>x_soud2_manual_bil_manual_billing_header</name>
            <roles/>
            <sys_class_name>sys_ui_section</sys_class_name>
            <sys_created_by>dyearsley</sys_created_by>
            <sys_created_on>2019-08-14 17:10:16</sys_created_on>
            <sys_customer_update>false</sys_customer_update>
            <sys_domain>global</sys_domain>
            <sys_id>8f0f4e89db17ff006c66d211ce9619c1</sys_id>
            <sys_mod_count>3</sys_mod_count>
            <sys_name>Notes</sys_name>
            <sys_overrides/>
            <sys_package display_value="Manual Billing" source="x_soud2_manual_bil">a369cbe31bf7e3005ae0c91e1e4bcb51</sys_package>
            <sys_policy/>
            <sys_replace_on_upgrade>false</sys_replace_on_upgrade>
            <sys_scope display_value="Manual Billing">a369cbe31bf7e3005ae0c91e1e4bcb51</sys_scope>
            <sys_update_name>sys_ui_section_8f0f4e89db17ff006c66d211ce9619c1</sys_update_name>
            <sys_updated_by>dyearsley</sys_updated_by>
            <sys_updated_on>2019-08-30 20:32:56</sys_updated_on>
            <sys_user/>
            <title>false</title>
            <view display_value="Default view" name="NULL">Default view</view>
            <view_name/>
        </sys_ui_section>
    </sys_ui_section>
<sys_update_version action="INSERT_OR_UPDATE">
        <action>DELETE</action>
        <application display_value="Manual Billing">a369cbe31bf7e3005ae0c91e1e4bcb51</application>
        <comments/>
        <file_path/>
        <instance_id>e1981d624f8a5604152a99701310c715</instance_id>
        <instance_name>utahdev1</instance_name>
        <name>sys_ui_section_8f0f4e89db17ff006c66d211ce9619c1</name>
        <order/>
        <payload><![CDATA[<?xml version="1.0" encoding="UTF-8"?><record_update>
    <sys_ui_section caption="Notes" section_id="8f0f4e89db17ff006c66d211ce9619c1" sys_domain="global" table="x_soud2_manual_bil_manual_billing_header" version="3" view="">
        <sys_ui_element action="INSERT_OR_UPDATE">
            <element>description</element>
            <position>0</position>
            <sys_created_by>dyearsley</sys_created_by>
            <sys_created_on>2019-10-03 20:42:06</sys_created_on>
            <sys_id>a10f9c19dbdc44107adf5dd5ce96195d</sys_id>
            <sys_mod_count>0</sys_mod_count>
            <sys_ui_formatter/>
            <sys_ui_section caption="Notes" display_value="Notes" name="x_soud2_manual_bil_manual_billing_header" sys_domain="global" view="Default view">8f0f4e89db17ff006c66d211ce9619c1</sys_ui_section>
            <sys_updated_by>dyearsley</sys_updated_by>
            <sys_updated_on>2019-10-03 20:42:06</sys_updated_on>
            <sys_user/>
            <type/>
        </sys_ui_element>
        <sys_ui_section action="INSERT_OR_UPDATE">
            <caption>Notes</caption>
            <header>false</header>
            <name>x_soud2_manual_bil_manual_billing_header</name>
            <roles/>
            <sys_class_name>sys_ui_section</sys_class_name>
            <sys_created_by>dyearsley</sys_created_by>
            <sys_created_on>2019-08-14 17:10:16</sys_created_on>
            <sys_customer_update>false</sys_customer_update>
            <sys_domain>global</sys_domain>
            <sys_id>8f0f4e89db17ff006c66d211ce9619c1</sys_id>
            <sys_mod_count>3</sys_mod_count>
            <sys_name>Notes</sys_name>
            <sys_overrides/>
            <sys_package display_value="Manual Billing" source="x_soud2_manual_bil">a369cbe31bf7e3005ae0c91e1e4bcb51</sys_package>
            <sys_policy/>
            <sys_replace_on_upgrade>false</sys_replace_on_upgrade>
            <sys_scope display_value="Manual Billing">a369cbe31bf7e3005ae0c91e1e4bcb51</sys_scope>
            <sys_update_name>sys_ui_section_8f0f4e89db17ff006c66d211ce9619c1</sys_update_name>
            <sys_updated_by>dyearsley</sys_updated_by>
            <sys_updated_on>2019-08-30 20:32:56</sys_updated_on>
            <sys_user/>
            <title>false</title>
            <view display_value="Default view" name="NULL">Default view</view>
            <view_name/>
        </sys_ui_section>
    </sys_ui_section>
</record_update>]]></payload>
        <payload_hash>-258231737</payload_hash>
        <record_name>Manual Billing</record_name>
        <reverted_from/>
        <source>2ffb15e1dbee80106c66d211ce9619b4</source>
        <source_table>sys_upgrade_history</source_table>
        <state>previous</state>
        <sys_created_by>dyearsley</sys_created_by>
        <sys_created_on>2020-01-24 16:08:32</sys_created_on>
        <sys_id>041c99e1dbee80106c66d211ce96195f</sys_id>
        <sys_mod_count>0</sys_mod_count>
        <sys_recorded_at>16fd84fe7340000001</sys_recorded_at>
        <sys_updated_by>dyearsley</sys_updated_by>
        <sys_updated_on>2020-01-24 16:08:32</sys_updated_on>
        <type>Form Layout</type>
        <update_guid>c01c99e1f5ee801048c16affeeb59d5f</update_guid>
        <update_guid_history>c01c99e1f5ee801048c16affeeb59d5f:-258231737</update_guid_history>
    </sys_update_version>
    <sys_metadata_delete action="INSERT_OR_UPDATE">
        <sys_audit_delete/>
        <sys_class_name>sys_metadata_delete</sys_class_name>
        <sys_created_by>dyearsley</sys_created_by>
        <sys_created_on>2020-02-05 14:49:41</sys_created_on>
        <sys_customer_update>false</sys_customer_update>
        <sys_db_object display_value="" name="sys_ui_section">sys_ui_section</sys_db_object>
        <sys_id>5b492ff3af7746fe91cff113a1a0d081</sys_id>
        <sys_metadata>8f0f4e89db17ff006c66d211ce9619c1</sys_metadata>
        <sys_mod_count>0</sys_mod_count>
        <sys_name>Notes</sys_name>
        <sys_package display_value="Manual Billing" source="x_soud2_manual_bil">a369cbe31bf7e3005ae0c91e1e4bcb51</sys_package>
        <sys_parent display_value="">a3bb92d41b79f3c054d843f9cd4bcbd1</sys_parent>
        <sys_policy/>
        <sys_replace_on_upgrade>false</sys_replace_on_upgrade>
        <sys_scope display_value="Manual Billing">a369cbe31bf7e3005ae0c91e1e4bcb51</sys_scope>
        <sys_scope_delete display_value="">279a16034fba4d2190cc50f42cc1ed81</sys_scope_delete>
        <sys_update_name>sys_ui_section_8f0f4e89db17ff006c66d211ce9619c1</sys_update_name>
        <sys_update_version display_value="sys_ui_section_8f0f4e89db17ff006c66d211ce9619c1">041c99e1dbee80106c66d211ce96195f</sys_update_version>
        <sys_updated_by>dyearsley</sys_updated_by>
        <sys_updated_on>2020-02-05 14:49:41</sys_updated_on>
    </sys_metadata_delete>
</record_update>
